{
  "scenarios": [
    {
      "id": "tohoku-2011",
      "displayName": "Tōhoku 2011 megathrust",
      "input": {
        "type": "seismic-megathrust",
        "magnitude": 9.1,
        "ruptureLengthM": 700000,
        "ruptureWidthM": 350000,
        "rakeDeg": 90,
        "dipDeg": 12,
        "centroidLat": 38.3,
        "centroidLon": 142.5,
        "basinDepthM": 4000
      },
      "domain": {
        "boundsDeg": [130, 180, 15, 50],
        "amrLevels": 2,
        "baseGridDeg": 0.5
      },
      "probes": [
        { "label": "DART 21413", "lat": 30.5, "lon": 152.1 }
      ],
      "publishedReferences": [
        { "label": "DART 21413", "peakAmplitudeM": 0.3, "source": "Satake 2013 BSSA 103(2B):1473" },
        { "label": "DART 21418", "peakAmplitudeM": 1.85, "source": "Satake 2013 Fig. 6" },
        {
          "label": "Hilo tide gauge",
          "peakAmplitudeM": 1.6,
          "source": "Yamazaki & Cheung 2011 GRL 38"
        }
      ]
    },
    {
      "id": "sumatra-2004",
      "displayName": "Sumatra-Andaman 2004 megathrust",
      "input": {
        "type": "seismic-megathrust",
        "magnitude": 9.1,
        "ruptureLengthM": 1300000,
        "ruptureWidthM": 650000,
        "_widthJustification": "Set to L/2 = 650 km to match Nimbus's L/W=2 subduction-megathrust aspect-ratio assumption (seismicTsunami.ts ruptureAspectRatio()). The historical Sumatra W was ~200 km but Nimbus's app-level model uses the aspect-ratio-derived W; the GeoClaw fixture is comparing against Nimbus's source, not the historical seafloor.",
        "rakeDeg": 90,
        "dipDeg": 8,
        "centroidLat": 6.0,
        "centroidLon": 94.0,
        "basinDepthM": 4000
      },
      "domain": {
        "boundsDeg": [60, 110, -20, 20],
        "amrLevels": 2,
        "baseGridDeg": 0.5
      },
      "probes": [
        { "label": "Cocos Island", "lat": -12.1, "lon": 96.9 },
        { "label": "Hanimaadhoo, Maldives", "lat": 6.8, "lon": 73.2 }
      ],
      "publishedReferences": [
        {
          "label": "Cocos Island deep-water",
          "peakAmplitudeM": 0.4,
          "source": "Bernard et al. 2006 Phil. Trans. R. Soc. A 364"
        },
        { "label": "Hanimaadhoo", "peakAmplitudeM": 1.6, "source": "Rabinovich et al. 2006 GRL 33" }
      ]
    },
    {
      "id": "krakatau-1883",
      "displayName": "Krakatau 1883 caldera collapse",
      "input": {
        "type": "volcanic-collapse",
        "collapseVolumeM3": 4.0e9,
        "collapseAreaM2": 8.0e7,
        "centroidLat": -6.1,
        "centroidLon": 105.42,
        "basinDepthM": 50,
        "deepBasinDepthM": 1500
      },
      "domain": {
        "boundsDeg": [102, 112, -8, -3],
        "amrLevels": 2,
        "baseGridDeg": 0.1
      },
      "probes": [
        { "label": "Anjer, Java tide gauge", "lat": -6.05, "lon": 105.97 },
        { "label": "Batavia (Jakarta) tide gauge", "lat": -6.13, "lon": 106.81 }
      ],
      "publishedReferences": [
        { "label": "Anjer", "peakAmplitudeM": 36.0, "source": "Verbeek 1885; Choi et al. 2003" },
        { "label": "Batavia tide gauge", "peakAmplitudeM": 2.4, "source": "Symons 1888" }
      ]
    },
    {
      "id": "storegga-8200bp",
      "displayName": "Storegga ~8200 BP submarine landslide",
      "input": {
        "type": "submarine-landslide",
        "slideVolumeM3": 3.0e12,
        "slideLengthM": 290000,
        "slideThicknessM": 220,
        "slopeRad": 0.087,
        "centroidLat": 65.0,
        "centroidLon": 2.0,
        "basinDepthM": 800
      },
      "domain": {
        "boundsDeg": [-15, 20, 55, 72],
        "amrLevels": 2,
        "baseGridDeg": 0.5
      },
      "probes": [
        { "label": "Norwegian coast, Sula", "lat": 63.5, "lon": 8.5 },
        { "label": "Shetland, Sullom Voe", "lat": 60.4, "lon": -1.3 }
      ],
      "publishedReferences": [
        {
          "label": "Sula sediment scour",
          "peakAmplitudeM": 10.0,
          "source": "Bondevik et al. 2005 QSR 24"
        },
        { "label": "Shetland", "peakAmplitudeM": 20.0, "source": "Smith et al. 2004 QSR 23" }
      ]
    },
    {
      "id": "cascadia-m9",
      "displayName": "Cascadia M9 reference scenario",
      "input": {
        "type": "seismic-megathrust",
        "magnitude": 9.0,
        "ruptureLengthM": 1100000,
        "ruptureWidthM": 550000,
        "_widthJustification": "Set to L/2 = 550 km to match Nimbus's L/W=2 subduction-megathrust aspect-ratio assumption.",
        "rakeDeg": 90,
        "dipDeg": 10,
        "centroidLat": 45.0,
        "centroidLon": -125.0,
        "basinDepthM": 3500
      },
      "domain": {
        "boundsDeg": [-150, -115, 30, 55],
        "amrLevels": 2,
        "baseGridDeg": 0.5
      },
      "probes": [
        { "label": "1000 km south (open Pacific)", "lat": 36.0, "lon": -125.0 },
        { "label": "1000 km west (open Pacific)", "lat": 45.0, "lon": -137.7 }
      ],
      "_probesNote": "Original coastal probes (Newport, Seaside, Crescent City) are inside the L=1100 km × W=550 km rupture footprint, where Nimbus's centred-Gaussian source over-predicts vs Okada's spatially-distributed uplift. Moved to open-Pacific 1000 km offsets so the 1D-radial far-field comparison is meaningful.",
      "publishedReferences": [
        {
          "label": "Newport reference",
          "peakAmplitudeM": 8.0,
          "source": "Witter et al. 2013 USGS Open-File 2013-1170"
        }
      ]
    },
    {
      "id": "eltanin-2.5ma",
      "displayName": "Eltanin 2.5 Ma deep-ocean asteroid impact",
      "input": {
        "type": "impact-deep-ocean",
        "impactorDiameterM": 1500,
        "impactorVelocityMPerS": 20000,
        "impactorDensityKgPerM3": 3000,
        "centroidLat": -57.3,
        "centroidLon": -90.5,
        "basinDepthM": 5000
      },
      "domain": {
        "boundsDeg": [-110, -70, -65, -45],
        "amrLevels": 2,
        "baseGridDeg": 1.0
      },
      "probes": [
        { "label": "500 km north", "lat": -52.8, "lon": -90.5 },
        { "label": "1000 km north", "lat": -48.3, "lon": -90.5 }
      ],
      "publishedReferences": [
        {
          "label": "Geological no-crater record",
          "peakAmplitudeM": 0.0,
          "source": "Gersonde et al. 1997 Nature 390:357"
        }
      ]
    },
    {
      "id": "custom-seismic-mw75-l300km",
      "displayName": "Custom — Mw 7.5, 300 km rupture (open Pacific)",
      "_purpose": "Tier-3 custom-input pin: small subduction event in the parameter space the user can configure in the app.",
      "input": {
        "type": "seismic-megathrust",
        "magnitude": 7.5,
        "ruptureLengthM": 300000,
        "ruptureWidthM": 80000,
        "rakeDeg": 90,
        "dipDeg": 12,
        "centroidLat": -25.0,
        "centroidLon": -135.0,
        "basinDepthM": 4000
      },
      "domain": {
        "boundsDeg": [-160, -110, -45, -5],
        "amrLevels": 2,
        "baseGridDeg": 1.0
      },
      "probes": [
        { "label": "500 km north", "lat": -20.5, "lon": -135.0 },
        { "label": "1000 km north", "lat": -16.0, "lon": -135.0 },
        { "label": "1500 km west", "lat": -25.0, "lon": -149.0 }
      ]
    },
    {
      "id": "custom-seismic-mw85-l700km",
      "displayName": "Custom — Mw 8.5, 700 km rupture (open Pacific)",
      "input": {
        "type": "seismic-megathrust",
        "magnitude": 8.5,
        "ruptureLengthM": 700000,
        "ruptureWidthM": 150000,
        "rakeDeg": 90,
        "dipDeg": 12,
        "centroidLat": -25.0,
        "centroidLon": -135.0,
        "basinDepthM": 4000
      },
      "domain": {
        "boundsDeg": [-170, -100, -50, 0],
        "amrLevels": 2,
        "baseGridDeg": 1.0
      },
      "probes": [
        { "label": "500 km north", "lat": -20.5, "lon": -135.0 },
        { "label": "1000 km north", "lat": -16.0, "lon": -135.0 },
        { "label": "2000 km north", "lat": -7.0, "lon": -135.0 }
      ]
    },
    {
      "id": "custom-seismic-mw95-l1500km",
      "displayName": "Custom — Mw 9.5, 1500 km rupture (open Pacific)",
      "input": {
        "type": "seismic-megathrust",
        "magnitude": 9.5,
        "ruptureLengthM": 1500000,
        "ruptureWidthM": 300000,
        "rakeDeg": 90,
        "dipDeg": 12,
        "centroidLat": -25.0,
        "centroidLon": -135.0,
        "basinDepthM": 4500
      },
      "domain": {
        "boundsDeg": [-180, -90, -55, 5],
        "amrLevels": 2,
        "baseGridDeg": 1.0
      },
      "probes": [
        { "label": "1000 km north", "lat": -16.0, "lon": -135.0 },
        { "label": "2000 km north", "lat": -7.0, "lon": -135.0 },
        { "label": "3000 km north", "lat": 2.0, "lon": -135.0 }
      ]
    },
    {
      "id": "custom-volcanic-small",
      "displayName": "Custom — small volcanic flank collapse (0.1 km³)",
      "input": {
        "type": "volcanic-collapse",
        "collapseVolumeM3": 1.0e8,
        "collapseAreaM2": 4.0e6,
        "slopeRad": 0.087,
        "centroidLat": -25.0,
        "centroidLon": -135.0,
        "basinDepthM": 1000
      },
      "domain": {
        "boundsDeg": [-145, -125, -35, -15],
        "amrLevels": 2,
        "baseGridDeg": 0.5
      },
      "probes": [
        { "label": "100 km", "lat": -24.1, "lon": -135.0 },
        { "label": "300 km", "lat": -22.3, "lon": -135.0 },
        { "label": "500 km", "lat": -20.5, "lon": -135.0 }
      ]
    },
    {
      "id": "custom-volcanic-large",
      "displayName": "Custom — large volcanic caldera collapse (20 km³)",
      "input": {
        "type": "volcanic-collapse",
        "collapseVolumeM3": 2.0e10,
        "collapseAreaM2": 4.0e8,
        "slopeRad": 0.087,
        "centroidLat": -25.0,
        "centroidLon": -135.0,
        "basinDepthM": 1500
      },
      "domain": {
        "boundsDeg": [-150, -120, -40, -10],
        "amrLevels": 2,
        "baseGridDeg": 0.5
      },
      "probes": [
        { "label": "200 km", "lat": -23.2, "lon": -135.0 },
        { "label": "500 km", "lat": -20.5, "lon": -135.0 },
        { "label": "1000 km", "lat": -16.0, "lon": -135.0 }
      ]
    },
    {
      "id": "custom-landslide-small",
      "displayName": "Custom — small submarine landslide (50 km³)",
      "input": {
        "type": "submarine-landslide",
        "slideVolumeM3": 5.0e10,
        "slideLengthM": 80000,
        "slopeRad": 0.087,
        "centroidLat": -25.0,
        "centroidLon": -135.0,
        "basinDepthM": 1500
      },
      "domain": {
        "boundsDeg": [-150, -120, -40, -10],
        "amrLevels": 2,
        "baseGridDeg": 0.5
      },
      "probes": [
        { "label": "200 km", "lat": -23.2, "lon": -135.0 },
        { "label": "500 km", "lat": -20.5, "lon": -135.0 },
        { "label": "1000 km", "lat": -16.0, "lon": -135.0 }
      ]
    },
    {
      "id": "custom-landslide-large",
      "displayName": "Custom — giant submarine landslide (5000 km³)",
      "input": {
        "type": "submarine-landslide",
        "slideVolumeM3": 5.0e12,
        "slideLengthM": 350000,
        "slopeRad": 0.087,
        "centroidLat": -25.0,
        "centroidLon": -135.0,
        "basinDepthM": 2000
      },
      "domain": {
        "boundsDeg": [-160, -110, -45, -5],
        "amrLevels": 2,
        "baseGridDeg": 1.0
      },
      "probes": [
        { "label": "500 km", "lat": -20.5, "lon": -135.0 },
        { "label": "1000 km", "lat": -16.0, "lon": -135.0 },
        { "label": "2000 km", "lat": -7.0, "lon": -135.0 }
      ]
    },
    {
      "id": "custom-impact-3km",
      "displayName": "Custom — 3 km asteroid, 4 km basin",
      "input": {
        "type": "impact-deep-ocean",
        "impactorDiameterM": 3000,
        "impactorVelocityMPerS": 20000,
        "impactorDensityKgPerM3": 3000,
        "centroidLat": -25.0,
        "centroidLon": -135.0,
        "basinDepthM": 4000
      },
      "domain": {
        "boundsDeg": [-180, -90, -55, 5],
        "amrLevels": 2,
        "baseGridDeg": 1.0
      },
      "probes": [
        { "label": "1000 km north", "lat": -16.0, "lon": -135.0 },
        { "label": "2000 km north", "lat": -7.0, "lon": -135.0 },
        { "label": "3000 km north", "lat": 2.0, "lon": -135.0 }
      ]
    }
  ],
  "_metadata": {
    "schemaVersion": 1,
    "format": "Each scenario.id matches a setrun.py template generated by setrun_template.py and a fixture file at src/physics/validation/geoclawFixtures/<id>.json. publishedReferences are NOT GeoClaw outputs; they are the historical observation we expect GeoClaw to reproduce. The actual GeoClaw output goes into the fixture file's geoclawProbes field.",
    "generatorRef": "scripts/geoclaw/run_scenario.py + extract_results.py"
  }
}
